AUTHORS.txt
CHANGES.txt
MANIFEST.in
README.txt
THANKS.txt
__init__.py
_registry.py
registry.py
setup.py
registry.egg-info/PKG-INFO
registry.egg-info/SOURCES.txt
registry.egg-info/dependency_links.txt
registry.egg-info/top_level.txt
test/__init__.py
test/test_registry.py